telegraph_api/__init__.py
telegraph_api/api.py
telegraph_api/exceptions.py
telegraph_api/html_transform.py
telegraph_api/html_transform_middlewares.py
telegraph_api/utils.py
telegraph_api/models/__init__.py
telegraph_api/models/account.py
telegraph_api/models/node.py
telegraph_api/models/page.py
telegraph_api/models/uploaded_file.py
telegraph_api-1.1.0.dist-info/LICENSE
telegraph_api-1.1.0.dist-info/METADATA
telegraph_api-1.1.0.dist-info/WHEEL
telegraph_api-1.1.0.dist-info/top_level.txt
telegraph_api-1.1.0.dist-info/RECORD
