Metadata-Version: 2.1
Name: telegraph-api
Version: 1.1.0
Summary: Asynchronus Python wrapper for telgra.ph API
Home-page: https://github.com/IvanProgramming/telegraph_api
Author: ivanprogramming
License: UNKNOWN
Project-URL: Bug Tracker, https://github.com/IvanProgramming/telegraph_api/issues
Platform: UNKNOWN
Classifier: Programming Language :: Python :: 3
Classifier: License :: OSI Approved :: MIT License
Classifier: Operating System :: OS Independent
Requires-Python: >=3.8
License-File: LICENSE
Requires-Dist: aiohttp
Requires-Dist: bs4
Requires-Dist: pydantic
Requires-Dist: setuptools
Requires-Dist: urllib3
